histpy/__init__.py
histpy/__version__.py
histpy/axes.py
histpy/axis.py
histpy/feature.py
histpy/healpix_axis.py
histpy/histogram.py
histpy/time_axis.py
histpy/time_axis_base.py
histpy/time_delta_axis.py
histpy-2.0.5.dist-info/METADATA
histpy-2.0.5.dist-info/WHEEL
histpy-2.0.5.dist-info/top_level.txt
histpy-2.0.5.dist-info/RECORD
