Metadata-Version: 2.4
Name: histpy
Version: 2.0.5
Home-page: https://gitlab.com/burstcube/histpy
Author: Israel Martinez
Author-email: imc@umd.edu
Requires-Dist: scipy>=1.11
Requires-Dist: matplotlib
Requires-Dist: h5py
Requires-Dist: sparse
Requires-Dist: astropy
Requires-Dist: mhealpy
Dynamic: author
Dynamic: author-email
Dynamic: description
Dynamic: description-content-type
Dynamic: home-page
Dynamic: requires-dist
